<?xml version="1.0" encoding="utf-8" ?><dwsync><file name="84cacd90b74c7cdf99fcb5b42d6335b4469262" server="ftp.alexmoen.com" local="3574306579" remote="3554607600" Dst="-1" /><file name="2d30f9bb5a4e228d70120612519634f3a87824" server="ftp.alexmoen.com" local="3574306579" remote="3554607600" Dst="-1" /><file name="9649c6559db76bbbec67487ae075950c50495b" server="ftp.alexmoen.com" local="3574306579" remote="3554780400" Dst="-1" /><file name="aa275e0321a8982f8340e3636a98aec7b18bdb" server="ftp.alexmoen.com" local="3574306580" remote="3554607600" Dst="-1" /><file name="c972b34f1aaa82a2d3a012c3d795a5a365f08d" server="ftp.alexmoen.com" local="3574306580" remote="3554607600" Dst="-1" /><file name="c9f4b23edfaeefbf5caedd8986cb67c0cb5bfb" server="ftp.alexmoen.com" local="3574306580" remote="3554607600" Dst="-1" /><file name="d98e66e2d9022501e304358872fa08400de016" server="ftp.alexmoen.com" local="3574306580" remote="3554607600" Dst="-1" /><file name="e040316bc36a2d8fc7ba881cebaf175fc05a91" server="ftp.alexmoen.com" local="3574306580" remote="3554607600" Dst="-1" /></dwsync>