<?xml version="1.0" encoding="utf-8" ?><dwsync><file name="0467889f23467c5f445577471fe3c8d989df1f" server="ftp.alexmoen.com" local="3574306369" remote="3554607600" Dst="-1" /><file name="3333da5f4179f962d304c5c5469e4f3ec592ab" server="ftp.alexmoen.com" local="3574306369" remote="3554607600" Dst="-1" /><file name="52cba05d0ad3109bd443c7d10d54709e220804" server="ftp.alexmoen.com" local="3574306369" remote="3554607600" Dst="-1" /><file name="81030b9a8df6fd4f37321aede62593193015a3" server="ftp.alexmoen.com" local="3574306370" remote="3554607600" Dst="-1" /><file name="830f672efa9aebee290bf8d15a525ec35ec833" server="ftp.alexmoen.com" local="3574306370" remote="3554607600" Dst="-1" /><file name="302e817a9dbdfad3d2e3157c79b06169efc075" server="ftp.alexmoen.com" local="3574306371" remote="3554607600" Dst="-1" /><file name="ae4102b9bfd0f43a6b7c24bbbba1e2f67d050e" server="ftp.alexmoen.com" local="3574306371" remote="3554780400" Dst="-1" /><file name="b0da9e9827630e699c9b89d061efa8600fe904" server="ftp.alexmoen.com" local="3574306372" remote="3554607600" Dst="-1" /><file name="bf5ae2592a380df71d3d86b6c19acf63c8b280" server="ftp.alexmoen.com" local="3574306375" remote="3554780400" Dst="-1" /></dwsync>